rym/token/__init__.py
rym/token/regex.py
rym/token/structures.py
rym/token/tokenizer.py
rym/token/tokenspec.py
rym/token/tokenspecgroup.py
rym_token-0.1.3.dist-info/METADATA
rym_token-0.1.3.dist-info/WHEEL
rym_token-0.1.3.dist-info/RECORD
