Metadata-Version: 2.1
Name: rym-token
Version: 0.1.3
Summary: A python library for tokenizing text.
Project-URL: Homepage, https://github.com/muppetjones/rym-py/tree/main/rym-token
Project-URL: Bug Tracker, https://github.com/muppetjones/rym-py/issues
Project-URL: Documentation, https://muppetjones.github.io/rym-py/rym-token
Author-email: Stephen Bush <muppetjones@gmail.com>
License: MIT
Classifier: License :: OSI Approved :: MIT License
Classifier: Operating System :: OS Independent
Classifier: Programming Language :: Python :: 3
Requires-Python: >=3.8
Provides-Extra: lint
Requires-Dist: black>=20.8b1; extra == 'lint'
Requires-Dist: flake8>=3.8; extra == 'lint'
Provides-Extra: test
Requires-Dist: coverage[toml]>=7.1.0; extra == 'test'
Requires-Dist: pytest-cov>=4.0.0; extra == 'test'
Requires-Dist: pytest>=6.2; extra == 'test'
